<?xml version="1.0" encoding="UTF-8"?>
<tv generator-info-name="WebGrab+Plus/w MDB &amp; REX Postprocess -- version V3.1.4.0 -- Jan van Straaten" generator-info-url="http://www.webgrabplus.com">
  <channel id="MULTISHOW">
    <display-name lang="en">Multishow</display-name>
    <icon src="https://oisa.tmsimg.com/assets/s78181_h3_aa.png" />
    <url>http://www.oi.com.br</url>
  </channel>
  <programme start="20210118001400 -0300" stop="20210118010400 -0300" channel="MULTISHOW">
    <title lang="en">Vai que Cola</title>
    <sub-title lang="en">Hoje É Dia de Karaokê</sub-title>
    <desc lang="en">O malandro Valdomiro se mete em uma falcatrua e, ao fugir da Polícia Federal, vai parar em uma pensão no subúrbio carioca. Dona Jô, dona do estabelecimento, apesar de saber do passado do vigarista, decide lhe dar uma chance. Waldomiro se torna hóspede da pensão e agora quer reescrever sua história. Só que para isso precisa lidar com as provocações do insolente Ferdinando, o assédio de Terezinha e as esquisitices do misterioso Wilson. Para completar a confusão, Jéssica, filha de Dona Jô, vive se desentendendo com o namorado Máicol, e a chegada da loira Velna, que se passa por uma gringa, aumenta ainda mais a bagunça.(n)</desc>
    <credits>
      <actor role="Dona Jô">Catarina Abdalla</actor>
      <actor role="Terezinha">Cacau Protásio</actor>
      <actor role="Jéssica">Samantha Schmütz</actor>
      <actor role="Ferdinando">Marcus Majella</actor>
      <actor role="Sanderson">Marcelo Médici</actor>
      <actor role="Reginél">Luis Lobianco</actor>
      <actor role="Zélio">Paulinho Serra</actor>
      <actor role="Gabi do Lins">Letícia Lima</actor>
      <actor role="Eletricsson">Rafael Infante</actor>
      <actor role="Bruno Surfistão">Alexandre Porpetone</actor>
      <writer>Leandro Soares</writer>
    </credits>
    <date>2020</date>
    <category lang="en">Comédia</category>
    <icon src="https://oisa.tmsimg.com/assets/p19130466_e_h10_aa.jpg" />
    <episode-num system="onscreen">S8 E23/40</episode-num>
    <rating>
      <value>12</value>
    </rating>
  </programme>
  <programme start="20210118010400 -0300" stop="20210118015000 -0300" channel="MULTISHOW">
    <title lang="en">Vai que Cola</title>
    <sub-title lang="en">O Baile do Caviar</sub-title>
    <desc lang="en">O malandro Valdomiro se mete em uma falcatrua e, ao fugir da Polícia Federal, vai parar em uma pensão no subúrbio carioca. Dona Jô, dona do estabelecimento, apesar de saber do passado do vigarista, decide lhe dar uma chance. Waldomiro se torna hóspede da pensão e agora quer reescrever sua história. Só que para isso precisa lidar com as provocações do insolente Ferdinando, o assédio de Terezinha e as esquisitices do misterioso Wilson. Para completar a confusão, Jéssica, filha de Dona Jô, vive se desentendendo com o namorado Máicol, e a chegada da loira Velna, que se passa por uma gringa, aumenta ainda mais a bagunça.(n)</desc>
    <credits>
      <actor role="Dona Jô">Catarina Abdalla</actor>
      <actor role="Terezinha">Cacau Protásio</actor>
      <actor role="Jéssica">Samantha Schmütz</actor>
      <actor role="Ferdinando">Marcus Majella</actor>
      <actor role="Sanderson">Marcelo Médici</actor>
      <actor role="Reginél">Luis Lobianco</actor>
      <actor role="Zélio">Paulinho Serra</actor>
      <actor role="Gabi do Lins">Letícia Lima</actor>
      <actor role="Eletricsson">Rafael Infante</actor>
      <actor role="Bruno Surfistão">Alexandre Porpetone</actor>
      <writer>Leandro Soares</writer>
    </credits>
    <date>2020</date>
    <category lang="en">Comédia</category>
    <icon src="https://oisa.tmsimg.com/assets/p19130447_e_h10_aa.jpg" />
    <episode-num system="onscreen">S8 E24/40</episode-num>
    <rating>
      <value>12</value>
    </rating>
  </programme>
  <programme start="20210118015000 -0300" stop="20210118023600 -0300" channel="MULTISHOW">
    <title lang="en">Vai que Cola</title>
    <sub-title lang="en">A Diarista</sub-title>
    <desc lang="en">O malandro Valdomiro se mete em uma falcatrua e, ao fugir da Polícia Federal, vai parar em uma pensão no subúrbio carioca. Dona Jô, dona do estabelecimento, apesar de saber do passado do vigarista, decide lhe dar uma chance. Waldomiro se torna hóspede da pensão e agora quer reescrever sua história. Só que para isso precisa lidar com as provocações do insolente Ferdinando, o assédio de Terezinha e as esquisitices do misterioso Wilson. Para completar a confusão, Jéssica, filha de Dona Jô, vive se desentendendo com o namorado Máicol, e a chegada da loira Velna, que se passa por uma gringa, aumenta ainda mais a bagunça.(n)</desc>
    <credits>
      <actor role="Dona Jô">Catarina Abdalla</actor>
      <actor role="Terezinha">Cacau Protásio</actor>
      <actor role="Jéssica">Samantha Schmütz</actor>
      <actor role="Ferdinando">Marcus Majella</actor>
      <actor role="Sanderson">Marcelo Médici</actor>
      <actor role="Reginél">Luis Lobianco</actor>
      <actor role="Zélio">Paulinho Serra</actor>
      <actor role="Gabi do Lins">Letícia Lima</actor>
      <actor role="Eletricsson">Rafael Infante</actor>
      <actor role="Bruno Surfistão">Alexandre Porpetone</actor>
      <writer>Leandro Soares</writer>
    </credits>
    <date>2020</date>
    <category lang="en">Comédia</category>
    <icon src="https://oisa.tmsimg.com/assets/p19130426_e_h10_aa.jpg" />
    <episode-num system="onscreen">S8 E25/40</episode-num>
    <rating>
      <value>12</value>
    </rating>
  </programme>
  <programme start="20210118023600 -0300" stop="20210118032200 -0300" channel="MULTISHOW">
    <title lang="en">Vai que Cola</title>
    <sub-title lang="en">Voleiblon</sub-title>
    <desc lang="en">O malandro Valdomiro se mete em uma falcatrua e, ao fugir da Polícia Federal, vai parar em uma pensão no subúrbio carioca. Dona Jô, dona do estabelecimento, apesar de saber do passado do vigarista, decide lhe dar uma chance. Waldomiro se torna hóspede da pensão e agora quer reescrever sua história. Só que para isso precisa lidar com as provocações do insolente Ferdinando, o assédio de Terezinha e as esquisitices do misterioso Wilson. Para completar a confusão, Jéssica, filha de Dona Jô, vive se desentendendo com o namorado Máicol, e a chegada da loira Velna, que se passa por uma gringa, aumenta ainda mais a bagunça.(n)</desc>
    <credits>
      <actor role="Dona Jô">Catarina Abdalla</actor>
      <actor role="Terezinha">Cacau Protásio</actor>
      <actor role="Jéssica">Samantha Schmütz</actor>
      <actor role="Ferdinando">Marcus Majella</actor>
      <actor role="Sanderson">Marcelo Médici</actor>
      <actor role="Reginél">Luis Lobianco</actor>
      <actor role="Zélio">Paulinho Serra</actor>
      <actor role="Gabi do Lins">Letícia Lima</actor>
      <actor role="Eletricsson">Rafael Infante</actor>
      <actor role="Bruno Surfistão">Alexandre Porpetone</actor>
      <writer>Leandro Soares</writer>
    </credits>
    <date>2020</date>
    <category lang="en">Comédia</category>
    <icon src="https://oisa.tmsimg.com/assets/p19130416_e_h8_aa.jpg" />
    <episode-num system="onscreen">S8 E26/40</episode-num>
    <rating>
      <value>12</value>
    </rating>
  </programme>
  <programme start="20210118032200 -0300" stop="20210118040900 -0300" channel="MULTISHOW">
    <title lang="en">Vai que Cola</title>
    <sub-title lang="en">O Dia do Enem</sub-title>
    <desc lang="en">O malandro Valdomiro se mete em uma falcatrua e, ao fugir da Polícia Federal, vai parar em uma pensão no subúrbio carioca. Dona Jô, dona do estabelecimento, apesar de saber do passado do vigarista, decide lhe dar uma chance. Waldomiro se torna hóspede da pensão e agora quer reescrever sua história. Só que para isso precisa lidar com as provocações do insolente Ferdinando, o assédio de Terezinha e as esquisitices do misterioso Wilson. Para completar a confusão, Jéssica, filha de Dona Jô, vive se desentendendo com o namorado Máicol, e a chegada da loira Velna, que se passa por uma gringa, aumenta ainda mais a bagunça.(n)</desc>
    <credits>
      <actor role="Dona Jô">Catarina Abdalla</actor>
      <actor role="Terezinha">Cacau Protásio</actor>
      <actor role="Jéssica">Samantha Schmütz</actor>
      <actor role="Ferdinando">Marcus Majella</actor>
      <actor role="Sanderson">Marcelo Médici</actor>
      <actor role="Reginél">Luis Lobianco</actor>
      <actor role="Zélio">Paulinho Serra</actor>
      <actor role="Gabi do Lins">Letícia Lima</actor>
      <actor role="Eletricsson">Rafael Infante</actor>
      <actor role="Bruno Surfistão">Alexandre Porpetone</actor>
      <writer>Leandro Soares</writer>
    </credits>
    <date>2020</date>
    <category lang="en">Comédia</category>
    <icon src="https://oisa.tmsimg.com/assets/p19130401_e_h8_aa.jpg" />
    <episode-num system="onscreen">S8 E27/40</episode-num>
    <rating>
      <value>12</value>
    </rating>
  </programme>
  <programme start="20210118040900 -0300" stop="20210118043900 -0300" channel="MULTISHOW">
    <title lang="en">Experimente</title>
    <sub-title lang="en">Jade Baraldo</sub-title>
    <desc lang="en">Conheça Jade Baraldo, nascida na cidade de Brusque, em Santa Catarina. Participou da edição de 2016 do "The Voice Brasil" e fez sucesso com o seu primeiro single, "Brasa".(n)</desc>
    <credits>
      <presenter>Guilherme Guedes</presenter>
    </credits>
    <date>2019</date>
    <category lang="en">Música</category>
    <category lang="en">Variedades</category>
    <icon src="https://oisa.tmsimg.com/assets/p17534502_e_h10_aa.jpg" />
    <episode-num system="onscreen">E9</episode-num>
    <rating>
      <value>12</value>
    </rating>
  </programme>
  <programme start="20210118043900 -0300" stop="20210118051000 -0300" channel="MULTISHOW">
    <title lang="en">Retrospectiva Big Brother Brasil</title>
    <sub-title lang="en">BBB 12 - Fael Cordeiro</sub-title>
    <desc lang="en">Relembre os melhores momentos de cada edição do BBB, com depoimentos exclusivos dos Brothers.(n)</desc>
    <date>2016</date>
    <category lang="en">Entretenimento</category>
    <category lang="en">Game show</category>
    <icon src="https://oisa.tmsimg.com/assets/p12470686_b_h10_ab.jpg" />
    <episode-num system="onscreen">S1 E12/20</episode-num>
    <rating>
      <value>12</value>
    </rating>
  </programme>
  <programme start="20210118051000 -0300" stop="20210118074000 -0300" channel="MULTISHOW">
    <title lang="en">Top TVZ</title>
    <desc lang="en">Melhores clipes da música nacional e internacional, com legendas em português.(n)</desc>
    <date>1999</date>
    <category lang="en">Música</category>
    <category lang="en">Variedades</category>
    <icon src="https://oisa.tmsimg.com/assets/p515764_b_h8_ac.jpg" />
    <rating>
      <value>12</value>
    </rating>
  </programme>
  <programme start="20210118074000 -0300" stop="20210118083900 -0300" channel="MULTISHOW">
    <title lang="en">Landmarks Live In Concert - Alicia Keys</title>
    <desc lang="en">Cantora e compositora vencedora do Grammy, Alicia Keys se apresenta em vários locais de Nova York.(n)</desc>
    <credits>
      <presenter>Chad Smith</presenter>
    </credits>
    <date>2017</date>
    <category lang="en">Especial</category>
    <category lang="en">Música</category>
    <icon src="https://oisa.tmsimg.com/assets/p13533565_b_h10_ab.jpg" />
    <rating>
      <value>L</value>
    </rating>
  </programme>
  <programme start="20210118083900 -0300" stop="20210118085800 -0300" channel="MULTISHOW">
    <title lang="en">O Show de Ed Bassmaster</title>
    <desc lang="en">Ed ajuda o cantor Justin Moore a se disfarçar para conhecer seu maior fã.(n)</desc>
    <credits>
      <actor>Ed Bassmaster</actor>
    </credits>
    <date>2016</date>
    <category lang="en">Comédia</category>
    <category lang="en">Reality</category>
    <icon src="https://oisa.tmsimg.com/assets/p12745122_e_h12_ab.jpg" />
    <episode-num system="onscreen">S1 E1/6</episode-num>
    <rating>
      <value>14</value>
    </rating>
  </programme>
  <programme start="20210118085800 -0300" stop="20210118092900 -0300" channel="MULTISHOW">
    <title lang="en">Tirou Onda</title>
    <desc lang="en">Os atores Noel Clarke e Jason Maza fazem o feitiço virar contra o feiticeiro; uma estrela é vítima em seu novo clube; um campeão olímpico no check-in do aeroporto; dois craques alegram desavisados torcedores; Hugh Jackman emociona um jovem fã em ação da Fundação Make-A-Wish.(n)</desc>
    <date>2020</date>
    <category lang="en">Comédia</category>
    <category lang="en">Entretenimento</category>
    <icon src="https://oisa.tmsimg.com/assets/p14921652_b_h10_ab.jpg" />
    <episode-num system="onscreen">S2 E2/3</episode-num>
    <rating>
      <value>10</value>
    </rating>
  </programme>
  <programme start="20210118092900 -0300" stop="20210118100000 -0300" channel="MULTISHOW">
    <title lang="en">Truques pela Rua</title>
    <sub-title lang="en">Sopão</sub-title>
    <desc lang="en">Em Brixton, Ryan conhece Solomon, o organizador de uma cozinha pública beneficente, e elabora um truque de mágica que recompensa o heroísmo de Solomon.(n)</desc>
    <date>2018</date>
    <category lang="en">Entretenimento</category>
    <icon src="https://oisa.tmsimg.com/assets/p16218985_b_h8_ad.jpg" />
    <episode-num system="onscreen">S1 E2/6</episode-num>
    <rating>
      <value>L</value>
    </rating>
  </programme>
  <programme start="20210118100000 -0300" stop="20210118102900 -0300" channel="MULTISHOW">
    <title lang="en">Quanto Vale o Mico?</title>
    <desc lang="en">Os competidores têm a oportunidade de ganhar 100 dólares, mas precisam usar a língua para obtê-lo.(n)</desc>
    <credits>
      <presenter>David Magidoff</presenter>
      <presenter>Derek Gaines</presenter>
    </credits>
    <date>2015</date>
    <category lang="en">Comédia</category>
    <category lang="en">Game show</category>
    <icon src="https://oisa.tmsimg.com/assets/p12288156_e_h10_ad.jpg" />
    <episode-num system="onscreen">S2 E6/6</episode-num>
    <rating>
      <value>16</value>
    </rating>
  </programme>
  <programme start="20210118102900 -0300" stop="20210118110100 -0300" channel="MULTISHOW">
    <title lang="en">Reclame</title>
    <desc lang="en">A 'Matéria de Capa' recebe o publicitário e artista plástico Marcello Serpa; veja o making of da nova campanha da Prudential do Brasil em parceria com a agência Made Rio e a Musikeria.(n)</desc>
    <credits>
      <presenter>Mariana Cartier</presenter>
    </credits>
    <date>2020</date>
    <category lang="en">Entretenimento</category>
    <icon src="https://oisa.tmsimg.com/assets/p876300_b_h10_ab.jpg" />
    <episode-num system="onscreen">E21</episode-num>
    <rating>
      <value>L</value>
    </rating>
  </programme>
  <programme start="20210118110100 -0300" stop="20210118111900 -0300" channel="MULTISHOW">
    <title lang="en">Encara o Desafio?</title>
    <desc lang="en">Pessoas selecionadas ao acaso realizam tarefas esdrúxulas em troca de dinheiro. Os convidados deste episódio são a comediante Jessimae Peluso e o mágico Penn Jillette.(n)</desc>
    <credits>
      <presenter>Theo Von</presenter>
    </credits>
    <date>2014</date>
    <category lang="en">Comédia</category>
    <category lang="en">Game show</category>
    <icon src="https://oisa.tmsimg.com/assets/p9991242_b_h10_ad.jpg" />
    <episode-num system="onscreen">S3 E7/7</episode-num>
    <rating>
      <value>14</value>
    </rating>
  </programme>
  <programme start="20210118111900 -0300" stop="20210118113000 -0300" channel="MULTISHOW">
    <title lang="en">Treme Treme</title>
    <desc lang="en">Baby vem feliz e Belmiro diz que está triste pois perdeu o seu porquinho; Baby dá a entender que foi ela que sumiu com o cofrinho e pegou o dinheiro para comprar ingressos para a boate; doutora Suslaine está saindo para trabalhar quando Belmiro a interrompe e pede uma consulta; ela dá o diagnóstico como falência da pleura e diz que seus órgãos irão morrer; Dona Fuxica conta dos vizinhos que se separaram mas continuam morando juntos e Belmiro se interessa pela fofoca.(n)</desc>
    <credits>
      <actor role="Belmiro">Gustavo Mendes</actor>
      <actor role="Gilmar">Fernando Caruso</actor>
      <actor role="Gagoberto/Baby Bobolete/Belmira/Margô/Inocencia/Bernadete">Caike Luna</actor>
      <actor role="Maria de Fátima">Larissa Câmara</actor>
      <actor role="Maria Eduarda">Bia Guedes</actor>
      <actor role="Baiano">Léo Castro</actor>
      <actor role="Sylmara Ciumenta">Mariana Cabral</actor>
      <actor role="Dona Eneida">Alexandre Scapini</actor>
      <actor role="Jaquisom David">Rafael Mazzi</actor>
      <actor role="Barbie">Renata Castro Barbosa</actor>
    </credits>
    <date>2018</date>
    <category lang="en">Sitcom</category>
    <icon src="https://oisa.tmsimg.com/assets/p15609402_e_h10_aa.jpg" />
    <episode-num system="onscreen">E10</episode-num>
    <rating>
      <value>12</value>
    </rating>
  </programme>
  <programme start="20210118113000 -0300" stop="20210118120000 -0300" channel="MULTISHOW">
    <title lang="en">Baby e Rose</title>
    <desc lang="en">Rose aconselha as telespectadoras a enfrentarem os seus problemas, assim como Baby que, apesar de feia, todos os dias se olha no espelho. Elas visitam um salão e Rose passa por uma transformação bem inusitada.(n)</desc>
    <credits>
      <actor role="Baby Bobolete">Caike Luna</actor>
      <actor role="Rose">Lindsay Paulino</actor>
    </credits>
    <date>2019</date>
    <category lang="en">Comédia</category>
    <icon src="https://oisa.tmsimg.com/assets/p17530877_e_h10_aa.jpg" />
    <episode-num system="onscreen">S2 E10/18</episode-num>
    <rating>
      <value>10</value>
    </rating>
  </programme>
  <programme start="20210118120000 -0300" stop="20210118123100 -0300" channel="MULTISHOW">
    <title lang="en">Anota Aí</title>
    <sub-title lang="en">10 Maneiras de Curtir a Natureza na África do Sul</sub-title>
    <desc lang="en">Titi Müller dá uma volta pelo mundo e traz dicas de hospedagem, beleza e alimentação. Com muito bom humor, ela passa por lugares imperdíveis e, às vezes, bastante inusitados.(n)</desc>
    <credits>
      <presenter>Titi Müller</presenter>
    </credits>
    <date>2019</date>
    <category lang="en">Viagem</category>
    <icon src="https://oisa.tmsimg.com/assets/p17681423_e_h10_aa.jpg" />
    <episode-num system="onscreen">S7 E6/8</episode-num>
    <rating>
      <value>12</value>
    </rating>
  </programme>
  <programme start="20210118123100 -0300" stop="20210118130000 -0300" channel="MULTISHOW">
    <title lang="en">Retrospectiva Big Brother Brasil</title>
    <sub-title lang="en">BBB 12 - Fael Cordeiro</sub-title>
    <desc lang="en">Relembre os melhores momentos de cada edição do BBB, com depoimentos exclusivos dos Brothers.(n)</desc>
    <date>2016</date>
    <category lang="en">Entretenimento</category>
    <category lang="en">Game show</category>
    <icon src="https://oisa.tmsimg.com/assets/p12470686_b_h10_ab.jpg" />
    <episode-num system="onscreen">S1 E12/20</episode-num>
    <rating>
      <value>12</value>
    </rating>
  </programme>
  <programme start="20210118130000 -0300" stop="20210118153000 -0300" channel="MULTISHOW">
    <title lang="en">TVZ</title>
    <desc lang="en">Os melhores clipes nacionais e internacionais das paradas musicais. Cada música apresenta letra e legenda.(n)</desc>
    <category lang="en">Música</category>
    <category lang="en">Variedades</category>
    <icon src="https://oisa.tmsimg.com/assets/p498480_b_h10_ab.jpg" />
    <rating>
      <value>12</value>
    </rating>
  </programme>
  <programme start="20210118153000 -0300" stop="20210118160000 -0300" channel="MULTISHOW">
    <title lang="en">Cassetadas da Internet</title>
    <desc lang="en">Agrupada em torno de temas fáceis de acompanhar, a série abrange uma grande variedade de clipes; de acrobacias com falhas épicas de profissionais e suas conquistas incríveis até os personagens mais estranhos da internet.(n)</desc>
    <date>2020</date>
    <category lang="en">Comédia</category>
    <icon src="https://oisa.tmsimg.com/assets/p17530898_b_h10_ac.jpg" />
    <episode-num system="onscreen">E14</episode-num>
    <rating>
      <value>12</value>
    </rating>
  </programme>
  <programme start="20210118160000 -0300" stop="20210118165100 -0300" channel="MULTISHOW">
    <title lang="en">Vai que Cola</title>
    <sub-title lang="en">O Dia do Enem</sub-title>
    <desc lang="en">O malandro Valdomiro se mete em uma falcatrua e, ao fugir da Polícia Federal, vai parar em uma pensão no subúrbio carioca. Dona Jô, dona do estabelecimento, apesar de saber do passado do vigarista, decide lhe dar uma chance. Waldomiro se torna hóspede da pensão e agora quer reescrever sua história. Só que para isso precisa lidar com as provocações do insolente Ferdinando, o assédio de Terezinha e as esquisitices do misterioso Wilson. Para completar a confusão, Jéssica, filha de Dona Jô, vive se desentendendo com o namorado Máicol, e a chegada da loira Velna, que se passa por uma gringa, aumenta ainda mais a bagunça.(n)</desc>
    <credits>
      <actor role="Dona Jô">Catarina Abdalla</actor>
      <actor role="Terezinha">Cacau Protásio</actor>
      <actor role="Jéssica">Samantha Schmütz</actor>
      <actor role="Ferdinando">Marcus Majella</actor>
      <actor role="Sanderson">Marcelo Médici</actor>
      <actor role="Reginél">Luis Lobianco</actor>
      <actor role="Zélio">Paulinho Serra</actor>
      <actor role="Gabi do Lins">Letícia Lima</actor>
      <actor role="Eletricsson">Rafael Infante</actor>
      <actor role="Bruno Surfistão">Alexandre Porpetone</actor>
      <writer>Leandro Soares</writer>
    </credits>
    <date>2020</date>
    <category lang="en">Comédia</category>
    <icon src="https://oisa.tmsimg.com/assets/p19130401_e_h8_aa.jpg" />
    <episode-num system="onscreen">S8 E27/40</episode-num>
    <rating>
      <value>12</value>
    </rating>
  </programme>
  <programme start="20210118165100 -0300" stop="20210118172400 -0300" channel="MULTISHOW">
    <title lang="en">Fábrica de Memes</title>
    <sub-title lang="en">Sobrevivente</sub-title>
    <desc lang="en">Às vezes, vale a pena arriscar.(n)</desc>
    <date>2019</date>
    <category lang="en">Comédia</category>
    <icon src="https://oisa.tmsimg.com/assets/p17747450_e_h11_ab.jpg" />
    <episode-num system="onscreen">S7 E7/7</episode-num>
    <rating>
      <value>12</value>
    </rating>
  </programme>
  <programme start="20210118172400 -0300" stop="20210118175600 -0300" channel="MULTISHOW">
    <title lang="en">Mágica de Rua</title>
    <desc lang="en">Veja truques de mágica e pegadinhas criativas.(n)</desc>
    <credits>
      <presenter>Eric Leclerc</presenter>
    </credits>
    <date>2016</date>
    <category lang="en">Reality</category>
    <icon src="https://oisa.tmsimg.com/assets/p13188887_e_h10_aa.jpg" />
    <episode-num system="onscreen">S1 E2/3</episode-num>
    <rating>
      <value>L</value>
    </rating>
  </programme>
  <programme start="20210118175600 -0300" stop="20210118182900 -0300" channel="MULTISHOW">
    <title lang="en">Tirou Onda</title>
    <desc lang="en">Com as participações de Tom Holland, Michael Ballack, Emma Bunton, Alan Shearer e Hulk Hogan.(n)</desc>
    <date>2020</date>
    <category lang="en">Comédia</category>
    <category lang="en">Entretenimento</category>
    <icon src="https://oisa.tmsimg.com/assets/p14921652_b_h10_ab.jpg" />
    <episode-num system="onscreen">S2 E3/3</episode-num>
    <rating>
      <value>10</value>
    </rating>
  </programme>
  <programme start="20210118182900 -0300" stop="20210118190200 -0300" channel="MULTISHOW">
    <title lang="en">Álbum Musical</title>
    <sub-title lang="en">Rimas e Batidas</sub-title>
    <desc lang="en">Conheça alguns dos melhores artistas do hip-hop nacional e entenda porque cada um deles é extremamente especial no que faz.(n)</desc>
    <credits>
      <presenter>Dedé Teicher</presenter>
      <presenter>Guilherme Guedes</presenter>
    </credits>
    <date>2017</date>
    <category lang="en">Entretenimento</category>
    <category lang="en">Música</category>
    <icon src="https://oisa.tmsimg.com/assets/p14800933_e_h11_aa.jpg" />
    <episode-num system="onscreen">S1 E2/4</episode-num>
    <rating>
      <value>10</value>
    </rating>
  </programme>
  <programme start="20210118190200 -0300" stop="20210118193000 -0300" channel="MULTISHOW">
    <title lang="en">Além da Ilha</title>
    <desc lang="en">Kenji some em um dos desafios dos hóspedes e Guta nota algo estranho com Theodoro quando começa a procurar pelas câmeras.(n)</desc>
    <credits>
      <actor role="Beto">Paulo Gustavo</actor>
      <actor role="Guta">Katiuscia Canoro</actor>
      <actor role="Sheila">Monique Alfradique</actor>
      <actor role="Bia">Letícia Lima</actor>
      <actor role="Cardoso">Gabriel Godoy</actor>
      <actor role="Theodoro">André Mattos</actor>
      <actor role="Tobias">Guilherme Piva</actor>
      <actor role="Inácio">Paulo Roque</actor>
      <actor role="Kenji Midoriya">Anderson Lau</actor>
      <actor role="Atílio Bueno">Breno Guimarães</actor>
      <writer>Andrea Batitucci</writer>
      <writer>Rosana Hermann</writer>
    </credits>
    <date>2018</date>
    <category lang="en">Comédia Dramática</category>
    <icon src="https://oisa.tmsimg.com/assets/p17155130_e_h10_aa.jpg" />
    <episode-num system="onscreen">S1 E5/10</episode-num>
    <rating>
      <value>12</value>
    </rating>
  </programme>
  <programme start="20210118193000 -0300" stop="20210118202800 -0300" channel="MULTISHOW">
    <title lang="en">Multi Tom</title>
    <sub-title lang="en">Carioca</sub-title>
    <desc lang="en">Ribamar e Carioca se empolgam na entrevista e fazem loucuras no palco; no "Tá Ok, Brasília!(n)</desc>
    <credits>
      <actor>Tom Cavalcante</actor>
    </credits>
    <date>2019</date>
    <category lang="en">Comédia</category>
    <category lang="en">Entretenimento</category>
    <icon src="https://oisa.tmsimg.com/assets/p16838455_e_h10_aa.jpg" />
    <episode-num system="onscreen">S4 E5/13</episode-num>
    <rating>
      <value>14</value>
    </rating>
  </programme>
  <programme start="20210118202800 -0300" stop="20210118210000 -0300" channel="MULTISHOW">
    <title lang="en">Retrospectiva Big Brother Brasil</title>
    <sub-title lang="en">BBB 13 - Fernanda Keulla</sub-title>
    <desc lang="en">Relembre os melhores momentos de cada edição do BBB, com depoimentos exclusivos dos Brothers.(n)</desc>
    <date>2016</date>
    <category lang="en">Entretenimento</category>
    <category lang="en">Game show</category>
    <icon src="https://oisa.tmsimg.com/assets/p12470686_b_h10_ab.jpg" />
    <episode-num system="onscreen">S1 E13/20</episode-num>
    <rating>
      <value>12</value>
    </rating>
  </programme>
  <programme start="20210118210000 -0300" stop="20210118213000 -0300" channel="MULTISHOW">
    <title lang="en">Lugar Incomum</title>
    <sub-title lang="en">Portugal</sub-title>
    <desc lang="en">Didi está em Lisboa e faz um passeio no Tram 28, o bondinho tradicional e popular entre os turistas. Ela ainda prova os famosos pasteis de Belém e dá uma volta de bicicleta do Cais do Sodré até Belém.(n)</desc>
    <credits>
      <presenter>Didi Wagner</presenter>
    </credits>
    <date>2015</date>
    <category lang="en">Viagem</category>
    <icon src="https://oisa.tmsimg.com/assets/p12850681_e_h8_ac.jpg" />
    <episode-num system="onscreen">S13 E1/2</episode-num>
    <rating>
      <value>L</value>
    </rating>
  </programme>
  <programme start="20210118213000 -0300" stop="20210118230000 -0300" channel="MULTISHOW">
    <title lang="en">TVZ</title>
    <desc lang="en">Os melhores clipes nacionais e internacionais das paradas musicais. Cada música apresenta letra e legenda.(n)</desc>
    <category lang="en">Música</category>
    <category lang="en">Variedades</category>
    <icon src="https://oisa.tmsimg.com/assets/p498480_b_h10_ab.jpg" />
    <rating>
      <value>12</value>
    </rating>
  </programme>
  <programme start="20210118230000 -0300" stop="20210118233000 -0300" channel="MULTISHOW">
    <title lang="en">Tô de Graça</title>
    <sub-title lang="en">Fruto Proibido</sub-title>
    <desc lang="en">Briti interpreta mal o jeito carinhoso da cunhada Sonaira e resolve investir nessa paixão.(n)</desc>
    <credits>
      <actor>Rodrigo Sant'Anna</actor>
      <actor>Roberta Rodrigues</actor>
      <actor>Eliezer Motta</actor>
      <actor>Nego do Borel</actor>
      <actor>Ernani Moraes</actor>
      <actor>Dhu Moraes</actor>
      <actor>Evelyn Castro</actor>
      <actor>Isabelle Marques</actor>
      <writer>Rodrigo Sant'Anna</writer>
      <writer>Denise Crispun</writer>
    </credits>
    <date>2019</date>
    <category lang="en">Comédia</category>
    <icon src="https://oisa.tmsimg.com/assets/p17175768_e_h10_aa.jpg" />
    <episode-num system="onscreen">S3 E8/29</episode-num>
    <rating>
      <value>12</value>
    </rating>
  </programme>
  <programme start="20210118233000 -0300" stop="20210119010000 -0300" channel="MULTISHOW">
    <title lang="en">The Voice+</title>
    <desc lang="en">Reality show musical em que quatro equipes de talentos a partir dos 60 anos lideradas por grandes nomes da música brasileira competem entre si. Na primeira fase, os jurados fazem as eliminações baseadas apenas na voz dos participantes.(n)</desc>
    <credits>
      <presenter>André Marques</presenter>
    </credits>
    <date>2021</date>
    <category lang="en">Música</category>
    <category lang="en">Reality</category>
    <icon src="https://oisa.tmsimg.com/assets/p19293539_b_h10_ab.jpg" />
    <episode-num system="onscreen">S1 E1/2</episode-num>
    <rating>
      <value>L</value>
    </rating>
  </programme>
  <programme start="20210119010000 -0300" stop="20210119014800 -0300" channel="MULTISHOW">
    <title lang="en">Vai que Cola</title>
    <sub-title lang="en">Vai Ter Carnaval Sim</sub-title>
    <desc lang="en">O malandro Valdomiro se mete em uma falcatrua e, ao fugir da Polícia Federal, vai parar em uma pensão no subúrbio carioca. Dona Jô, dona do estabelecimento, apesar de saber do passado do vigarista, decide lhe dar uma chance. Waldomiro se torna hóspede da pensão e agora quer reescrever sua história. Só que para isso precisa lidar com as provocações do insolente Ferdinando, o assédio de Terezinha e as esquisitices do misterioso Wilson. Para completar a confusão, Jéssica, filha de Dona Jô, vive se desentendendo com o namorado Máicol, e a chegada da loira Velna, que se passa por uma gringa, aumenta ainda mais a bagunça.(n)</desc>
    <credits>
      <actor role="Dona Jô">Catarina Abdalla</actor>
      <actor role="Terezinha">Cacau Protásio</actor>
      <actor role="Jéssica">Samantha Schmütz</actor>
      <actor role="Ferdinando">Marcus Majella</actor>
      <actor role="Sanderson">Marcelo Médici</actor>
      <actor role="Reginél">Luis Lobianco</actor>
      <actor role="Zélio">Paulinho Serra</actor>
      <actor role="Gabi do Lins">Letícia Lima</actor>
      <actor role="Eletricsson">Rafael Infante</actor>
      <actor role="Bruno Surfistão">Alexandre Porpetone</actor>
      <writer>Leandro Soares</writer>
    </credits>
    <date>2020</date>
    <category lang="en">Comédia</category>
    <icon src="https://oisa.tmsimg.com/assets/p19130386_e_h10_ab.jpg" />
    <episode-num system="onscreen">S8 E29/40</episode-num>
    <rating>
      <value>12</value>
    </rating>
  </programme>
  <programme start="20210119014800 -0300" stop="20210119023700 -0300" channel="MULTISHOW">
    <title lang="en">Vai que Cola</title>
    <sub-title lang="en">Bão Demais!</sub-title>
    <desc lang="en">O malandro Valdomiro se mete em uma falcatrua e, ao fugir da Polícia Federal, vai parar em uma pensão no subúrbio carioca. Dona Jô, dona do estabelecimento, apesar de saber do passado do vigarista, decide lhe dar uma chance. Waldomiro se torna hóspede da pensão e agora quer reescrever sua história. Só que para isso precisa lidar com as provocações do insolente Ferdinando, o assédio de Terezinha e as esquisitices do misterioso Wilson. Para completar a confusão, Jéssica, filha de Dona Jô, vive se desentendendo com o namorado Máicol, e a chegada da loira Velna, que se passa por uma gringa, aumenta ainda mais a bagunça.(n)</desc>
    <credits>
      <actor role="Dona Jô">Catarina Abdalla</actor>
      <actor role="Terezinha">Cacau Protásio</actor>
      <actor role="Jéssica">Samantha Schmütz</actor>
      <actor role="Ferdinando">Marcus Majella</actor>
      <actor role="Sanderson">Marcelo Médici</actor>
      <actor role="Reginél">Luis Lobianco</actor>
      <actor role="Zélio">Paulinho Serra</actor>
      <actor role="Gabi do Lins">Letícia Lima</actor>
      <actor role="Eletricsson">Rafael Infante</actor>
      <actor role="Bruno Surfistão">Alexandre Porpetone</actor>
      <writer>Leandro Soares</writer>
    </credits>
    <date>2020</date>
    <category lang="en">Comédia</category>
    <icon src="https://oisa.tmsimg.com/assets/p19130378_e_h10_ab.jpg" />
    <episode-num system="onscreen">S8 E30/40</episode-num>
    <rating>
      <value>12</value>
    </rating>
  </programme>
  <programme start="20210119023700 -0300" stop="20210119030700 -0300" channel="MULTISHOW">
    <title lang="en">Baby e Rose</title>
    <desc lang="en">Rose dá algumas dicas de como se livrar daqueles parentes que vêm passar o Natal e nunca mais vão embora. No número musical, Baby e Rose cantam uma paródia de "Menino da Porteira".(n)</desc>
    <credits>
      <actor role="Baby Bobolete">Caike Luna</actor>
      <actor role="Rose">Lindsay Paulino</actor>
    </credits>
    <date>2019</date>
    <category lang="en">Comédia</category>
    <icon src="https://oisa.tmsimg.com/assets/p17534538_e_h10_aa.jpg" />
    <episode-num system="onscreen">S2 E11/18</episode-num>
    <rating>
      <value>10</value>
    </rating>
  </programme>
  <programme start="20210119030700 -0300" stop="20210119033500 -0300" channel="MULTISHOW">
    <title lang="en">Férias em Família</title>
    <sub-title lang="en">Sagrada Família</sub-title>
    <desc lang="en">Depois de passar férias com uma série de trapalhadas em Portugal, a família Rangel resolve esticar a viagem até a Espanha. A primeira parada é Barcelona e a família descobre que caiu em outro golpe.(n)</desc>
    <credits>
      <actor role="Cafu">Luis Lobianco</actor>
      <actor role="Duda">Sulivã Bispo</actor>
      <actor role="Tia Iraci">Cristina Pereira</actor>
      <actor role="Bel">Clara Tiezzi</actor>
      <actor role="Jacinta">Fafá de Belém</actor>
      <actor role="Sandrão">Luciana Paes</actor>
      <writer>Fábio Mendes</writer>
    </credits>
    <date>2020</date>
    <category lang="en">Comédia</category>
    <icon src="https://oisa.tmsimg.com/assets/p17863220_e_h10_aa.jpg" />
    <episode-num system="onscreen">S2 E1/10</episode-num>
    <rating>
      <value>10</value>
    </rating>
  </programme>
  <programme start="20210119033500 -0300" stop="20210119040500 -0300" channel="MULTISHOW">
    <title lang="en">Truque de Humor</title>
    <desc lang="en">Gabriel e PyongLee misturam mágica e diversão com anéis entrelaçados e mágica interativa.(n)</desc>
    <credits>
      <presenter>Gabriel Louchard</presenter>
    </credits>
    <date>2018</date>
    <category lang="en">Comédia</category>
    <category lang="en">Entretenimento</category>
    <icon src="https://oisa.tmsimg.com/assets/p15445547_e_h10_aa.jpg" />
    <episode-num system="onscreen">S2 E11/15</episode-num>
    <rating>
      <value>12</value>
    </rating>
  </programme>
  <programme start="20210119040500 -0300" stop="20210119043400 -0300" channel="MULTISHOW">
    <title lang="en">Além da Ilha</title>
    <desc lang="en">Enquanto todos tentam desvendar o sumiço de Kenji, Guta pega o livro de Beto e vai sozinha ao cemitério. Lá, ela descobre algo muito estranho e corre para contar a Beto.(n)</desc>
    <credits>
      <actor role="Beto">Paulo Gustavo</actor>
      <actor role="Guta">Katiuscia Canoro</actor>
      <actor role="Sheila">Monique Alfradique</actor>
      <actor role="Bia">Letícia Lima</actor>
      <actor role="Cardoso">Gabriel Godoy</actor>
      <actor role="Theodoro">André Mattos</actor>
      <actor role="Tobias">Guilherme Piva</actor>
      <actor role="Inácio">Paulo Roque</actor>
      <actor role="Kenji Midoriya">Anderson Lau</actor>
      <actor role="Atílio Bueno">Breno Guimarães</actor>
      <writer>Andrea Batitucci</writer>
      <writer>Rosana Hermann</writer>
    </credits>
    <date>2018</date>
    <category lang="en">Comédia Dramática</category>
    <icon src="https://oisa.tmsimg.com/assets/p17155131_e_h10_aa.jpg" />
    <episode-num system="onscreen">S1 E6/10</episode-num>
    <rating>
      <value>12</value>
    </rating>
  </programme>
  <programme start="20210119043400 -0300" stop="20210119050600 -0300" channel="MULTISHOW">
    <title lang="en">Retrospectiva Big Brother Brasil</title>
    <sub-title lang="en">BBB 13 - Fernanda Keulla</sub-title>
    <desc lang="en">Relembre os melhores momentos de cada edição do BBB, com depoimentos exclusivos dos Brothers.(n)</desc>
    <date>2016</date>
    <category lang="en">Entretenimento</category>
    <category lang="en">Game show</category>
    <icon src="https://oisa.tmsimg.com/assets/p12470686_b_h10_ab.jpg" />
    <episode-num system="onscreen">S1 E13/20</episode-num>
    <rating>
      <value>12</value>
    </rating>
  </programme>
  <programme start="20210119050600 -0300" stop="20210119073600 -0300" channel="MULTISHOW">
    <title lang="en">TVZ</title>
    <desc lang="en">Os melhores clipes nacionais e internacionais das paradas musicais. Cada música apresenta letra e legenda.(n)</desc>
    <category lang="en">Música</category>
    <category lang="en">Variedades</category>
    <icon src="https://oisa.tmsimg.com/assets/p498480_b_h10_ab.jpg" />
    <rating>
      <value>12</value>
    </rating>
  </programme>
  <programme start="20210119073600 -0300" stop="20210119080800 -0300" channel="MULTISHOW">
    <title lang="en">Anota Aí</title>
    <sub-title lang="en">10 Maneiras de Curtir a Natureza na África do Sul</sub-title>
    <desc lang="en">Titi Müller dá uma volta pelo mundo e traz dicas de hospedagem, beleza e alimentação. Com muito bom humor, ela passa por lugares imperdíveis e, às vezes, bastante inusitados.(n)</desc>
    <credits>
      <presenter>Titi Müller</presenter>
    </credits>
    <date>2019</date>
    <category lang="en">Viagem</category>
    <icon src="https://oisa.tmsimg.com/assets/p17681423_e_h10_aa.jpg" />
    <episode-num system="onscreen">S7 E6/8</episode-num>
    <rating>
      <value>12</value>
    </rating>
  </programme>
  <programme start="20210119080800 -0300" stop="20210119083900 -0300" channel="MULTISHOW">
    <title lang="en">Cassetadas da Internet</title>
    <desc lang="en">Agrupada em torno de temas fáceis de acompanhar, a série abrange uma grande variedade de clipes; de acrobacias com falhas épicas de profissionais e suas conquistas incríveis até os personagens mais estranhos da internet.(n)</desc>
    <date>2020</date>
    <category lang="en">Comédia</category>
    <icon src="https://oisa.tmsimg.com/assets/p17530898_b_h10_ac.jpg" />
    <episode-num system="onscreen">E14</episode-num>
    <rating>
      <value>12</value>
    </rating>
  </programme>
  <programme start="20210119083900 -0300" stop="20210119091100 -0300" channel="MULTISHOW">
    <title lang="en">Truques pela Rua</title>
    <sub-title lang="en">Sopão</sub-title>
    <desc lang="en">Em Brixton, Ryan conhece Solomon, o organizador de uma cozinha pública beneficente, e elabora um truque de mágica que recompensa o heroísmo de Solomon.(n)</desc>
    <date>2018</date>
    <category lang="en">Entretenimento</category>
    <icon src="https://oisa.tmsimg.com/assets/p16218985_b_h8_ad.jpg" />
    <episode-num system="onscreen">S1 E2/6</episode-num>
    <rating>
      <value>L</value>
    </rating>
  </programme>
  <programme start="20210119091100 -0300" stop="20210119094300 -0300" channel="MULTISHOW">
    <title lang="en">Mágica de Rua</title>
    <desc lang="en">Veja truques de mágica e pegadinhas criativas.(n)</desc>
    <credits>
      <presenter>Eric Leclerc</presenter>
    </credits>
    <date>2016</date>
    <category lang="en">Reality</category>
    <icon src="https://oisa.tmsimg.com/assets/p13188887_e_h10_aa.jpg" />
    <episode-num system="onscreen">S1 E2/3</episode-num>
    <rating>
      <value>L</value>
    </rating>
  </programme>
  <programme start="20210119094300 -0300" stop="20210119100000 -0300" channel="MULTISHOW">
    <title lang="en">O Show de Ed Bassmaster</title>
    <desc lang="en">Ed ajuda o cantor Justin Moore a se disfarçar para conhecer seu maior fã.(n)</desc>
    <credits>
      <actor>Ed Bassmaster</actor>
    </credits>
    <date>2016</date>
    <category lang="en">Comédia</category>
    <category lang="en">Reality</category>
    <icon src="https://oisa.tmsimg.com/assets/p12745122_e_h12_ab.jpg" />
    <episode-num system="onscreen">S1 E1/6</episode-num>
    <rating>
      <value>14</value>
    </rating>
  </programme>
  <programme start="20210119100000 -0300" stop="20210119113000 -0300" channel="MULTISHOW">
    <title lang="en">The Voice+</title>
    <desc lang="en">Reality show musical em que quatro equipes de talentos a partir dos 60 anos lideradas por grandes nomes da música brasileira competem entre si. Na primeira fase, os jurados fazem as eliminações baseadas apenas na voz dos participantes.(n)</desc>
    <credits>
      <presenter>André Marques</presenter>
    </credits>
    <date>2021</date>
    <category lang="en">Música</category>
    <category lang="en">Reality</category>
    <icon src="https://oisa.tmsimg.com/assets/p19293539_b_h10_ab.jpg" />
    <episode-num system="onscreen">S1 E1/2</episode-num>
    <rating>
      <value>L</value>
    </rating>
  </programme>
  <programme start="20210119113000 -0300" stop="20210119120000 -0300" channel="MULTISHOW">
    <title lang="en">Baby e Rose</title>
    <desc lang="en">Rose dá algumas dicas de como se livrar daqueles parentes que vêm passar o Natal e nunca mais vão embora. No número musical, Baby e Rose cantam uma paródia de "Menino da Porteira".(n)</desc>
    <credits>
      <actor role="Baby Bobolete">Caike Luna</actor>
      <actor role="Rose">Lindsay Paulino</actor>
    </credits>
    <date>2019</date>
    <category lang="en">Comédia</category>
    <icon src="https://oisa.tmsimg.com/assets/p17534538_e_h10_aa.jpg" />
    <episode-num system="onscreen">S2 E11/18</episode-num>
    <rating>
      <value>10</value>
    </rating>
  </programme>
  <programme start="20210119120000 -0300" stop="20210119123000 -0300" channel="MULTISHOW">
    <title lang="en">Tô de Graça</title>
    <sub-title lang="en">É um Pássaro? É um Avião? É a Briti?</sub-title>
    <desc lang="en">Briti é contratada por Pará, mas não tem ideia de que está sendo usada para contrabandear produtos.(n)</desc>
    <credits>
      <actor>Rodrigo Sant'Anna</actor>
      <actor>Roberta Rodrigues</actor>
      <actor>Eliezer Motta</actor>
      <actor>Nego do Borel</actor>
      <actor>Ernani Moraes</actor>
      <actor>Dhu Moraes</actor>
      <actor>Evelyn Castro</actor>
      <actor>Isabelle Marques</actor>
      <writer>Rodrigo Sant'Anna</writer>
      <writer>Denise Crispun</writer>
    </credits>
    <date>2019</date>
    <category lang="en">Comédia</category>
    <icon src="https://oisa.tmsimg.com/assets/p17175765_e_h10_aa.jpg" />
    <episode-num system="onscreen">S3 E5/29</episode-num>
    <rating>
      <value>12</value>
    </rating>
  </programme>
  <programme start="20210119123000 -0300" stop="20210119130000 -0300" channel="MULTISHOW">
    <title lang="en">Retrospectiva Big Brother Brasil</title>
    <sub-title lang="en">BBB 13 - Fernanda Keulla</sub-title>
    <desc lang="en">Relembre os melhores momentos de cada edição do BBB, com depoimentos exclusivos dos Brothers.(n)</desc>
    <date>2016</date>
    <category lang="en">Entretenimento</category>
    <category lang="en">Game show</category>
    <icon src="https://oisa.tmsimg.com/assets/p12470686_b_h10_ab.jpg" />
    <episode-num system="onscreen">S1 E13/20</episode-num>
    <rating>
      <value>12</value>
    </rating>
  </programme>
  <programme start="20210119130000 -0300" stop="20210119153000 -0300" channel="MULTISHOW">
    <title lang="en">TVZ</title>
    <desc lang="en">Os melhores clipes nacionais e internacionais das paradas musicais. Cada música apresenta letra e legenda.(n)</desc>
    <category lang="en">Música</category>
    <category lang="en">Variedades</category>
    <icon src="https://oisa.tmsimg.com/assets/p498480_b_h10_ab.jpg" />
    <rating>
      <value>12</value>
    </rating>
  </programme>
  <programme start="20210119153000 -0300" stop="20210119160100 -0300" channel="MULTISHOW">
    <title lang="en">Landmarks Live In Concert - Alicia Keys</title>
    <desc lang="en">Cantora e compositora vencedora do Grammy, Alicia Keys se apresenta em vários locais de Nova York.(n)</desc>
    <credits>
      <presenter>Chad Smith</presenter>
    </credits>
    <date>2017</date>
    <category lang="en">Especial</category>
    <category lang="en">Música</category>
    <icon src="https://oisa.tmsimg.com/assets/p13533565_b_h10_ab.jpg" />
    <rating>
      <value>L</value>
    </rating>
  </programme>
  <programme start="20210119160100 -0300" stop="20210119165400 -0300" channel="MULTISHOW">
    <title lang="en">Vai que Cola</title>
    <sub-title lang="en">Vai Ter Carnaval Sim</sub-title>
    <desc lang="en">O malandro Valdomiro se mete em uma falcatrua e, ao fugir da Polícia Federal, vai parar em uma pensão no subúrbio carioca. Dona Jô, dona do estabelecimento, apesar de saber do passado do vigarista, decide lhe dar uma chance. Waldomiro se torna hóspede da pensão e agora quer reescrever sua história. Só que para isso precisa lidar com as provocações do insolente Ferdinando, o assédio de Terezinha e as esquisitices do misterioso Wilson. Para completar a confusão, Jéssica, filha de Dona Jô, vive se desentendendo com o namorado Máicol, e a chegada da loira Velna, que se passa por uma gringa, aumenta ainda mais a bagunça.(n)</desc>
    <credits>
      <actor role="Dona Jô">Catarina Abdalla</actor>
      <actor role="Terezinha">Cacau Protásio</actor>
      <actor role="Jéssica">Samantha Schmütz</actor>
      <actor role="Ferdinando">Marcus Majella</actor>
      <actor role="Sanderson">Marcelo Médici</actor>
      <actor role="Reginél">Luis Lobianco</actor>
      <actor role="Zélio">Paulinho Serra</actor>
      <actor role="Gabi do Lins">Letícia Lima</actor>
      <actor role="Eletricsson">Rafael Infante</actor>
      <actor role="Bruno Surfistão">Alexandre Porpetone</actor>
      <writer>Leandro Soares</writer>
    </credits>
    <date>2020</date>
    <category lang="en">Comédia</category>
    <icon src="https://oisa.tmsimg.com/assets/p19130386_e_h10_ab.jpg" />
    <episode-num system="onscreen">S8 E29/40</episode-num>
    <rating>
      <value>12</value>
    </rating>
  </programme>
  <programme start="20210119165400 -0300" stop="20210119175600 -0300" channel="MULTISHOW">
    <title lang="en">Um Jogo Quase Impossível</title>
    <desc lang="en">Competidores corajosos participam de jogos incrivelmente simples, mas insanamente difíceis.(n)</desc>
    <date>2016</date>
    <category lang="en">Comédia</category>
    <category lang="en">Game show</category>
    <icon src="https://oisa.tmsimg.com/assets/p12147717_b_h10_ay.jpg" />
    <episode-num system="onscreen">S2 E6/6</episode-num>
    <rating>
      <value>12</value>
    </rating>
  </programme>
  <programme start="20210119175600 -0300" stop="20210119185600 -0300" channel="MULTISHOW">
    <title lang="en">Versões</title>
    <sub-title lang="en">Rodrigo Lampreia Canta Seu Jorge</sub-title>
    <desc lang="en">Artistas brasileiros são convidados para fazer suas versões de clássicos da música. A cada episódio, uma banda ou artista é homenageado.(n)</desc>
    <credits>
      <presenter>Debora Teicher</presenter>
    </credits>
    <date>2020</date>
    <category lang="en">Entretenimento</category>
    <category lang="en">Música</category>
    <icon src="https://oisa.tmsimg.com/assets/p19121423_e_h10_aa.jpg" />
    <episode-num system="onscreen">S6 E9/9</episode-num>
    <rating>
      <value>10</value>
    </rating>
  </programme>
  <programme start="20210119185600 -0300" stop="20210119192800 -0300" channel="MULTISHOW">
    <title lang="en">Vai pra Onde?</title>
    <sub-title lang="en">Cuba Natural Esportiva</sub-title>
    <desc lang="en">Nesse episódio, Bruno De Luca nos mostra um pouco das belezas naturais e esportivas de Cuba. Começando pela linda praia de Varadero, passando pelo badalado point de encontro em Malecón.(n)</desc>
    <credits>
      <presenter>Bruno de Luca</presenter>
    </credits>
    <date>2016</date>
    <category lang="en">Viagem</category>
    <icon src="https://oisa.tmsimg.com/assets/p13385734_e_h10_ab.jpg" />
    <episode-num system="onscreen">S12 E4/6</episode-num>
    <rating>
      <value>12</value>
    </rating>
  </programme>
  <programme start="20210119192800 -0300" stop="20210119202900 -0300" channel="MULTISHOW">
    <title lang="en">Multi Tom</title>
    <sub-title lang="en">Leandro Hassum</sub-title>
    <desc lang="en">Ribamar entrevista o engraçadíssimo Leandro Hassum; a confusão está armada no quadro "Tá Ok, Brasília!(n)</desc>
    <credits>
      <actor>Tom Cavalcante</actor>
    </credits>
    <date>2019</date>
    <category lang="en">Comédia</category>
    <category lang="en">Entretenimento</category>
    <icon src="https://oisa.tmsimg.com/assets/p16836686_e_h10_aa.jpg" />
    <episode-num system="onscreen">S4 E1/13</episode-num>
    <rating>
      <value>14</value>
    </rating>
  </programme>
  <programme start="20210119202900 -0300" stop="20210119210000 -0300" channel="MULTISHOW">
    <title lang="en">Retrospectiva Big Brother Brasil</title>
    <sub-title lang="en">BBB 14 - Vanessa Mesquita</sub-title>
    <desc lang="en">Relembre os melhores momentos de cada edição do BBB, com depoimentos exclusivos dos Brothers.(n)</desc>
    <date>2016</date>
    <category lang="en">Entretenimento</category>
    <category lang="en">Game show</category>
    <icon src="https://oisa.tmsimg.com/assets/p12470686_b_h10_ab.jpg" />
    <episode-num system="onscreen">S1 E14/20</episode-num>
    <rating>
      <value>12</value>
    </rating>
  </programme>
  <programme start="20210119210000 -0300" stop="20210119213000 -0300" channel="MULTISHOW">
    <title lang="en">Roteiro das Ondas - Indonésia</title>
    <sub-title lang="en">Nas Ondas de Nusa Lembongan - Bali</sub-title>
    <desc lang="en">A ilha de Nusa Lembongan fica bem perto de Bali, com fácil acesso e é o tipo de lugar que vai além do surfe: menos urbanizado, com belezas naturais exorbitantes, perfeito para relaxar. Conheça outros lugares e ondas aos arredores da ilha.(n)</desc>
    <date>2018</date>
    <category lang="en">Aventura</category>
    <category lang="en">Viagem</category>
    <icon src="https://oisa.tmsimg.com/assets/p15547073_e_h11_aa.jpg" />
    <episode-num system="onscreen">E8</episode-num>
    <rating>
      <value>L</value>
    </rating>
  </programme>
  <programme start="20210119213000 -0300" stop="20210119230000 -0300" channel="MULTISHOW">
    <title lang="en">TVZ</title>
    <desc lang="en">Os melhores clipes nacionais e internacionais das paradas musicais. Cada música apresenta letra e legenda.(n)</desc>
    <category lang="en">Música</category>
    <category lang="en">Variedades</category>
    <icon src="https://oisa.tmsimg.com/assets/p498480_b_h10_ab.jpg" />
    <rating>
      <value>12</value>
    </rating>
  </programme>
  <programme start="20210119230000 -0300" stop="20210119233000 -0300" channel="MULTISHOW">
    <title lang="en">Tô de Graça</title>
    <sub-title lang="en">Fruto Proibido</sub-title>
    <desc lang="en">Briti interpreta mal o jeito carinhoso da cunhada Sonaira e resolve investir nessa paixão.(n)</desc>
    <credits>
      <actor>Rodrigo Sant'Anna</actor>
      <actor>Roberta Rodrigues</actor>
      <actor>Eliezer Motta</actor>
      <actor>Nego do Borel</actor>
      <actor>Ernani Moraes</actor>
      <actor>Dhu Moraes</actor>
      <actor>Evelyn Castro</actor>
      <actor>Isabelle Marques</actor>
      <writer>Rodrigo Sant'Anna</writer>
      <writer>Denise Crispun</writer>
    </credits>
    <date>2019</date>
    <category lang="en">Comédia</category>
    <icon src="https://oisa.tmsimg.com/assets/p17175768_e_h10_aa.jpg" />
    <episode-num system="onscreen">S3 E8/29</episode-num>
    <rating>
      <value>12</value>
    </rating>
  </programme>
  <programme start="20210119233000 -0300" stop="20210120010000 -0300" channel="MULTISHOW">
    <title lang="en">The Voice+</title>
    <desc lang="en">Reality show musical em que quatro equipes de talentos a partir dos 60 anos lideradas por grandes nomes da música brasileira competem entre si. Na primeira fase, os jurados fazem as eliminações baseadas apenas na voz dos participantes.(n)</desc>
    <credits>
      <presenter>André Marques</presenter>
    </credits>
    <date>2021</date>
    <category lang="en">Música</category>
    <category lang="en">Reality</category>
    <icon src="https://oisa.tmsimg.com/assets/p19293539_b_h10_ab.jpg" />
    <episode-num system="onscreen">S1 E1/2</episode-num>
    <rating>
      <value>L</value>
    </rating>
  </programme>
  <programme start="20210120010000 -0300" stop="20210120014800 -0300" channel="MULTISHOW">
    <title lang="en">Vai que Cola</title>
    <sub-title lang="en">Vai Ter Carnaval Sim</sub-title>
    <desc lang="en">O malandro Valdomiro se mete em uma falcatrua e, ao fugir da Polícia Federal, vai parar em uma pensão no subúrbio carioca. Dona Jô, dona do estabelecimento, apesar de saber do passado do vigarista, decide lhe dar uma chance. Waldomiro se torna hóspede da pensão e agora quer reescrever sua história. Só que para isso precisa lidar com as provocações do insolente Ferdinando, o assédio de Terezinha e as esquisitices do misterioso Wilson. Para completar a confusão, Jéssica, filha de Dona Jô, vive se desentendendo com o namorado Máicol, e a chegada da loira Velna, que se passa por uma gringa, aumenta ainda mais a bagunça.(n)</desc>
    <credits>
      <actor role="Dona Jô">Catarina Abdalla</actor>
      <actor role="Terezinha">Cacau Protásio</actor>
      <actor role="Jéssica">Samantha Schmütz</actor>
      <actor role="Ferdinando">Marcus Majella</actor>
      <actor role="Sanderson">Marcelo Médici</actor>
      <actor role="Reginél">Luis Lobianco</actor>
      <actor role="Zélio">Paulinho Serra</actor>
      <actor role="Gabi do Lins">Letícia Lima</actor>
      <actor role="Eletricsson">Rafael Infante</actor>
      <actor role="Bruno Surfistão">Alexandre Porpetone</actor>
      <writer>Leandro Soares</writer>
    </credits>
    <date>2020</date>
    <category lang="en">Comédia</category>
    <icon src="https://oisa.tmsimg.com/assets/p19130386_e_h10_ab.jpg" />
    <episode-num system="onscreen">S8 E29/40</episode-num>
    <rating>
      <value>12</value>
    </rating>
  </programme>
  <programme start="20210120014800 -0300" stop="20210120023700 -0300" channel="MULTISHOW">
    <title lang="en">Vai que Cola</title>
    <sub-title lang="en">Bão Demais!</sub-title>
    <desc lang="en">O malandro Valdomiro se mete em uma falcatrua e, ao fugir da Polícia Federal, vai parar em uma pensão no subúrbio carioca. Dona Jô, dona do estabelecimento, apesar de saber do passado do vigarista, decide lhe dar uma chance. Waldomiro se torna hóspede da pensão e agora quer reescrever sua história. Só que para isso precisa lidar com as provocações do insolente Ferdinando, o assédio de Terezinha e as esquisitices do misterioso Wilson. Para completar a confusão, Jéssica, filha de Dona Jô, vive se desentendendo com o namorado Máicol, e a chegada da loira Velna, que se passa por uma gringa, aumenta ainda mais a bagunça.(n)</desc>
    <credits>
      <actor role="Dona Jô">Catarina Abdalla</actor>
      <actor role="Terezinha">Cacau Protásio</actor>
      <actor role="Jéssica">Samantha Schmütz</actor>
      <actor role="Ferdinando">Marcus Majella</actor>
      <actor role="Sanderson">Marcelo Médici</actor>
      <actor role="Reginél">Luis Lobianco</actor>
      <actor role="Zélio">Paulinho Serra</actor>
      <actor role="Gabi do Lins">Letícia Lima</actor>
      <actor role="Eletricsson">Rafael Infante</actor>
      <actor role="Bruno Surfistão">Alexandre Porpetone</actor>
      <writer>Leandro Soares</writer>
    </credits>
    <date>2020</date>
    <category lang="en">Comédia</category>
    <icon src="https://oisa.tmsimg.com/assets/p19130378_e_h10_ab.jpg" />
    <episode-num system="onscreen">S8 E30/40</episode-num>
    <rating>
      <value>12</value>
    </rating>
  </programme>
  <programme start="20210120023700 -0300" stop="20210120030700 -0300" channel="MULTISHOW">
    <title lang="en">Baby e Rose</title>
    <desc lang="en">Rose dá algumas dicas de como se livrar daqueles parentes que vêm passar o Natal e nunca mais vão embora. No número musical, Baby e Rose cantam uma paródia de "Menino da Porteira".(n)</desc>
    <credits>
      <actor role="Baby Bobolete">Caike Luna</actor>
      <actor role="Rose">Lindsay Paulino</actor>
    </credits>
    <date>2019</date>
    <category lang="en">Comédia</category>
    <icon src="https://oisa.tmsimg.com/assets/p17534538_e_h10_aa.jpg" />
    <episode-num system="onscreen">S2 E11/18</episode-num>
    <rating>
      <value>10</value>
    </rating>
  </programme>
  <programme start="20210120030700 -0300" stop="20210120033500 -0300" channel="MULTISHOW">
    <title lang="en">Férias em Família</title>
    <sub-title lang="en">Sagrada Família</sub-title>
    <desc lang="en">Depois de passar férias com uma série de trapalhadas em Portugal, a família Rangel resolve esticar a viagem até a Espanha. A primeira parada é Barcelona e a família descobre que caiu em outro golpe.(n)</desc>
    <credits>
      <actor role="Cafu">Luis Lobianco</actor>
      <actor role="Duda">Sulivã Bispo</actor>
      <actor role="Tia Iraci">Cristina Pereira</actor>
      <actor role="Bel">Clara Tiezzi</actor>
      <actor role="Jacinta">Fafá de Belém</actor>
      <actor role="Sandrão">Luciana Paes</actor>
      <writer>Fábio Mendes</writer>
    </credits>
    <date>2020</date>
    <category lang="en">Comédia</category>
    <icon src="https://oisa.tmsimg.com/assets/p17863220_e_h10_aa.jpg" />
    <episode-num system="onscreen">S2 E1/10</episode-num>
    <rating>
      <value>10</value>
    </rating>
  </programme>
  <programme start="20210120033500 -0300" stop="20210120040500 -0300" channel="MULTISHOW">
    <title lang="en">Truque de Humor</title>
    <desc lang="en">Gabriel e PyongLee misturam mágica e diversão com anéis entrelaçados e mágica interativa.(n)</desc>
    <credits>
      <presenter>Gabriel Louchard</presenter>
    </credits>
    <date>2018</date>
    <category lang="en">Comédia</category>
    <category lang="en">Entretenimento</category>
    <icon src="https://oisa.tmsimg.com/assets/p15445547_e_h10_aa.jpg" />
    <episode-num system="onscreen">S2 E11/15</episode-num>
    <rating>
      <value>12</value>
    </rating>
  </programme>
  <programme start="20210120040500 -0300" stop="20210120043400 -0300" channel="MULTISHOW">
    <title lang="en">Além da Ilha</title>
    <desc lang="en">Enquanto todos tentam desvendar o sumiço de Kenji, Guta pega o livro de Beto e vai sozinha ao cemitério. Lá, ela descobre algo muito estranho e corre para contar a Beto.(n)</desc>
    <credits>
      <actor role="Beto">Paulo Gustavo</actor>
      <actor role="Guta">Katiuscia Canoro</actor>
      <actor role="Sheila">Monique Alfradique</actor>
      <actor role="Bia">Letícia Lima</actor>
      <actor role="Cardoso">Gabriel Godoy</actor>
      <actor role="Theodoro">André Mattos</actor>
      <actor role="Tobias">Guilherme Piva</actor>
      <actor role="Inácio">Paulo Roque</actor>
      <actor role="Kenji Midoriya">Anderson Lau</actor>
      <actor role="Atílio Bueno">Breno Guimarães</actor>
      <writer>Andrea Batitucci</writer>
      <writer>Rosana Hermann</writer>
    </credits>
    <date>2018</date>
    <category lang="en">Comédia Dramática</category>
    <icon src="https://oisa.tmsimg.com/assets/p17155131_e_h10_aa.jpg" />
    <episode-num system="onscreen">S1 E6/10</episode-num>
    <rating>
      <value>12</value>
    </rating>
  </programme>
  <programme start="20210120043400 -0300" stop="20210120050600 -0300" channel="MULTISHOW">
    <title lang="en">Retrospectiva Big Brother Brasil</title>
    <sub-title lang="en">BBB 13 - Fernanda Keulla</sub-title>
    <desc lang="en">Relembre os melhores momentos de cada edição do BBB, com depoimentos exclusivos dos Brothers.(n)</desc>
    <date>2016</date>
    <category lang="en">Entretenimento</category>
    <category lang="en">Game show</category>
    <icon src="https://oisa.tmsimg.com/assets/p12470686_b_h10_ab.jpg" />
    <episode-num system="onscreen">S1 E13/20</episode-num>
    <rating>
      <value>12</value>
    </rating>
  </programme>
  <programme start="20210120050600 -0300" stop="20210120073600 -0300" channel="MULTISHOW">
    <title lang="en">TVZ</title>
    <desc lang="en">Os melhores clipes nacionais e internacionais das paradas musicais. Cada música apresenta letra e legenda.(n)</desc>
    <category lang="en">Música</category>
    <category lang="en">Variedades</category>
    <icon src="https://oisa.tmsimg.com/assets/p498480_b_h10_ab.jpg" />
    <rating>
      <value>12</value>
    </rating>
  </programme>
  <programme start="20210120073600 -0300" stop="20210120080800 -0300" channel="MULTISHOW">
    <title lang="en">Anota Aí</title>
    <sub-title lang="en">10 Maneiras de Curtir a Natureza na África do Sul</sub-title>
    <desc lang="en">Titi Müller dá uma volta pelo mundo e traz dicas de hospedagem, beleza e alimentação. Com muito bom humor, ela passa por lugares imperdíveis e, às vezes, bastante inusitados.(n)</desc>
    <credits>
      <presenter>Titi Müller</presenter>
    </credits>
    <date>2019</date>
    <category lang="en">Viagem</category>
    <icon src="https://oisa.tmsimg.com/assets/p17681423_e_h10_aa.jpg" />
    <episode-num system="onscreen">S7 E6/8</episode-num>
    <rating>
      <value>12</value>
    </rating>
  </programme>
  <programme start="20210120080800 -0300" stop="20210120083900 -0300" channel="MULTISHOW">
    <title lang="en">Cassetadas da Internet</title>
    <desc lang="en">Agrupada em torno de temas fáceis de acompanhar, a série abrange uma grande variedade de clipes; de acrobacias com falhas épicas de profissionais e suas conquistas incríveis até os personagens mais estranhos da internet.(n)</desc>
    <date>2020</date>
    <category lang="en">Comédia</category>
    <icon src="https://oisa.tmsimg.com/assets/p17530898_b_h10_ac.jpg" />
    <episode-num system="onscreen">E14</episode-num>
    <rating>
      <value>12</value>
    </rating>
  </programme>
  <programme start="20210120083900 -0300" stop="20210120091100 -0300" channel="MULTISHOW">
    <title lang="en">Truques pela Rua</title>
    <sub-title lang="en">Sopão</sub-title>
    <desc lang="en">Em Brixton, Ryan conhece Solomon, o organizador de uma cozinha pública beneficente, e elabora um truque de mágica que recompensa o heroísmo de Solomon.(n)</desc>
    <date>2018</date>
    <category lang="en">Entretenimento</category>
    <icon src="https://oisa.tmsimg.com/assets/p16218985_b_h8_ad.jpg" />
    <episode-num system="onscreen">S1 E2/6</episode-num>
    <rating>
      <value>L</value>
    </rating>
  </programme>
  <programme start="20210120091100 -0300" stop="20210120094300 -0300" channel="MULTISHOW">
    <title lang="en">Mágica de Rua</title>
    <desc lang="en">Veja truques de mágica e pegadinhas criativas.(n)</desc>
    <credits>
      <presenter>Eric Leclerc</presenter>
    </credits>
    <date>2016</date>
    <category lang="en">Reality</category>
    <icon src="https://oisa.tmsimg.com/assets/p13188887_e_h10_aa.jpg" />
    <episode-num system="onscreen">S1 E2/3</episode-num>
    <rating>
      <value>L</value>
    </rating>
  </programme>
  <programme start="20210120094300 -0300" stop="20210120100000 -0300" channel="MULTISHOW">
    <title lang="en">O Show de Ed Bassmaster</title>
    <desc lang="en">Ed ajuda o cantor Justin Moore a se disfarçar para conhecer seu maior fã.(n)</desc>
    <credits>
      <actor>Ed Bassmaster</actor>
    </credits>
    <date>2016</date>
    <category lang="en">Comédia</category>
    <category lang="en">Reality</category>
    <icon src="https://oisa.tmsimg.com/assets/p12745122_e_h12_ab.jpg" />
    <episode-num system="onscreen">S1 E1/6</episode-num>
    <rating>
      <value>14</value>
    </rating>
  </programme>
  <programme start="20210120100000 -0300" stop="20210120113000 -0300" channel="MULTISHOW">
    <title lang="en">The Voice+</title>
    <desc lang="en">Reality show musical em que quatro equipes de talentos a partir dos 60 anos lideradas por grandes nomes da música brasileira competem entre si. Na primeira fase, os jurados fazem as eliminações baseadas apenas na voz dos participantes.(n)</desc>
    <credits>
      <presenter>André Marques</presenter>
    </credits>
    <date>2021</date>
    <category lang="en">Música</category>
    <category lang="en">Reality</category>
    <icon src="https://oisa.tmsimg.com/assets/p19293539_b_h10_ab.jpg" />
    <episode-num system="onscreen">S1 E1/2</episode-num>
    <rating>
      <value>L</value>
    </rating>
  </programme>
  <programme start="20210120113000 -0300" stop="20210120120000 -0300" channel="MULTISHOW">
    <title lang="en">Baby e Rose</title>
    <desc lang="en">Rose dá algumas dicas de como se livrar daqueles parentes que vêm passar o Natal e nunca mais vão embora. No número musical, Baby e Rose cantam uma paródia de "Menino da Porteira".(n)</desc>
    <credits>
      <actor role="Baby Bobolete">Caike Luna</actor>
      <actor role="Rose">Lindsay Paulino</actor>
    </credits>
    <date>2019</date>
    <category lang="en">Comédia</category>
    <icon src="https://oisa.tmsimg.com/assets/p17534538_e_h10_aa.jpg" />
    <episode-num system="onscreen">S2 E11/18</episode-num>
    <rating>
      <value>10</value>
    </rating>
  </programme>
  <programme start="20210120120000 -0300" stop="20210120123000 -0300" channel="MULTISHOW">
    <title lang="en">Tô de Graça</title>
    <sub-title lang="en">É um Pássaro? É um Avião? É a Briti?</sub-title>
    <desc lang="en">Briti é contratada por Pará, mas não tem ideia de que está sendo usada para contrabandear produtos.(n)</desc>
    <credits>
      <actor>Rodrigo Sant'Anna</actor>
      <actor>Roberta Rodrigues</actor>
      <actor>Eliezer Motta</actor>
      <actor>Nego do Borel</actor>
      <actor>Ernani Moraes</actor>
      <actor>Dhu Moraes</actor>
      <actor>Evelyn Castro</actor>
      <actor>Isabelle Marques</actor>
      <writer>Rodrigo Sant'Anna</writer>
      <writer>Denise Crispun</writer>
    </credits>
    <date>2019</date>
    <category lang="en">Comédia</category>
    <icon src="https://oisa.tmsimg.com/assets/p17175765_e_h10_aa.jpg" />
    <episode-num system="onscreen">S3 E5/29</episode-num>
    <rating>
      <value>12</value>
    </rating>
  </programme>
  <programme start="20210120123000 -0300" stop="20210120130000 -0300" channel="MULTISHOW">
    <title lang="en">Retrospectiva Big Brother Brasil</title>
    <sub-title lang="en">BBB 13 - Fernanda Keulla</sub-title>
    <desc lang="en">Relembre os melhores momentos de cada edição do BBB, com depoimentos exclusivos dos Brothers.(n)</desc>
    <date>2016</date>
    <category lang="en">Entretenimento</category>
    <category lang="en">Game show</category>
    <icon src="https://oisa.tmsimg.com/assets/p12470686_b_h10_ab.jpg" />
    <episode-num system="onscreen">S1 E13/20</episode-num>
    <rating>
      <value>12</value>
    </rating>
  </programme>
  <programme start="20210120130000 -0300" stop="20210120153000 -0300" channel="MULTISHOW">
    <title lang="en">TVZ</title>
    <desc lang="en">Os melhores clipes nacionais e internacionais das paradas musicais. Cada música apresenta letra e legenda.(n)</desc>
    <category lang="en">Música</category>
    <category lang="en">Variedades</category>
    <icon src="https://oisa.tmsimg.com/assets/p498480_b_h10_ab.jpg" />
    <rating>
      <value>12</value>
    </rating>
  </programme>
  <programme start="20210120153000 -0300" stop="20210120160100 -0300" channel="MULTISHOW">
    <title lang="en">Landmarks Live In Concert - Alicia Keys</title>
    <desc lang="en">Cantora e compositora vencedora do Grammy, Alicia Keys se apresenta em vários locais de Nova York.(n)</desc>
    <credits>
      <presenter>Chad Smith</presenter>
    </credits>
    <date>2017</date>
    <category lang="en">Especial</category>
    <category lang="en">Música</category>
    <icon src="https://oisa.tmsimg.com/assets/p13533565_b_h10_ab.jpg" />
    <rating>
      <value>L</value>
    </rating>
  </programme>
  <programme start="20210120160100 -0300" stop="20210120165400 -0300" channel="MULTISHOW">
    <title lang="en">Vai que Cola</title>
    <sub-title lang="en">Vai Ter Carnaval Sim</sub-title>
    <desc lang="en">O malandro Valdomiro se mete em uma falcatrua e, ao fugir da Polícia Federal, vai parar em uma pensão no subúrbio carioca. Dona Jô, dona do estabelecimento, apesar de saber do passado do vigarista, decide lhe dar uma chance. Waldomiro se torna hóspede da pensão e agora quer reescrever sua história. Só que para isso precisa lidar com as provocações do insolente Ferdinando, o assédio de Terezinha e as esquisitices do misterioso Wilson. Para completar a confusão, Jéssica, filha de Dona Jô, vive se desentendendo com o namorado Máicol, e a chegada da loira Velna, que se passa por uma gringa, aumenta ainda mais a bagunça.(n)</desc>
    <credits>
      <actor role="Dona Jô">Catarina Abdalla</actor>
      <actor role="Terezinha">Cacau Protásio</actor>
      <actor role="Jéssica">Samantha Schmütz</actor>
      <actor role="Ferdinando">Marcus Majella</actor>
      <actor role="Sanderson">Marcelo Médici</actor>
      <actor role="Reginél">Luis Lobianco</actor>
      <actor role="Zélio">Paulinho Serra</actor>
      <actor role="Gabi do Lins">Letícia Lima</actor>
      <actor role="Eletricsson">Rafael Infante</actor>
      <actor role="Bruno Surfistão">Alexandre Porpetone</actor>
      <writer>Leandro Soares</writer>
    </credits>
    <date>2020</date>
    <category lang="en">Comédia</category>
    <icon src="https://oisa.tmsimg.com/assets/p19130386_e_h10_ab.jpg" />
    <episode-num system="onscreen">S8 E29/40</episode-num>
    <rating>
      <value>12</value>
    </rating>
  </programme>
  <programme start="20210120165400 -0300" stop="20210120175600 -0300" channel="MULTISHOW">
    <title lang="en">Um Jogo Quase Impossível</title>
    <desc lang="en">Competidores corajosos participam de jogos incrivelmente simples, mas insanamente difíceis.(n)</desc>
    <date>2016</date>
    <category lang="en">Comédia</category>
    <category lang="en">Game show</category>
    <icon src="https://oisa.tmsimg.com/assets/p12147717_b_h10_ay.jpg" />
    <episode-num system="onscreen">S2 E6/6</episode-num>
    <rating>
      <value>12</value>
    </rating>
  </programme>
  <programme start="20210120175600 -0300" stop="20210120185600 -0300" channel="MULTISHOW">
    <title lang="en">Versões</title>
    <sub-title lang="en">Rodrigo Lampreia Canta Seu Jorge</sub-title>
    <desc lang="en">Artistas brasileiros são convidados para fazer suas versões de clássicos da música. A cada episódio, uma banda ou artista é homenageado.(n)</desc>
    <credits>
      <presenter>Debora Teicher</presenter>
    </credits>
    <date>2020</date>
    <category lang="en">Entretenimento</category>
    <category lang="en">Música</category>
    <icon src="https://oisa.tmsimg.com/assets/p19121423_e_h10_aa.jpg" />
    <episode-num system="onscreen">S6 E9/9</episode-num>
    <rating>
      <value>10</value>
    </rating>
  </programme>
  <programme start="20210120185600 -0300" stop="20210120192800 -0300" channel="MULTISHOW">
    <title lang="en">Vai pra Onde?</title>
    <sub-title lang="en">Cuba Natural Esportiva</sub-title>
    <desc lang="en">Nesse episódio, Bruno De Luca nos mostra um pouco das belezas naturais e esportivas de Cuba. Começando pela linda praia de Varadero, passando pelo badalado point de encontro em Malecón.(n)</desc>
    <credits>
      <presenter>Bruno de Luca</presenter>
    </credits>
    <date>2016</date>
    <category lang="en">Viagem</category>
    <icon src="https://oisa.tmsimg.com/assets/p13385734_e_h10_ab.jpg" />
    <episode-num system="onscreen">S12 E4/6</episode-num>
    <rating>
      <value>12</value>
    </rating>
  </programme>
  <programme start="20210120192800 -0300" stop="20210120202900 -0300" channel="MULTISHOW">
    <title lang="en">Multi Tom</title>
    <sub-title lang="en">Leandro Hassum</sub-title>
    <desc lang="en">Ribamar entrevista o engraçadíssimo Leandro Hassum; a confusão está armada no quadro "Tá Ok, Brasília!(n)</desc>
    <credits>
      <actor>Tom Cavalcante</actor>
    </credits>
    <date>2019</date>
    <category lang="en">Comédia</category>
    <category lang="en">Entretenimento</category>
    <icon src="https://oisa.tmsimg.com/assets/p16836686_e_h10_aa.jpg" />
    <episode-num system="onscreen">S4 E1/13</episode-num>
    <rating>
      <value>14</value>
    </rating>
  </programme>
  <programme start="20210120202900 -0300" stop="20210120210000 -0300" channel="MULTISHOW">
    <title lang="en">Retrospectiva Big Brother Brasil</title>
    <sub-title lang="en">BBB 14 - Vanessa Mesquita</sub-title>
    <desc lang="en">Relembre os melhores momentos de cada edição do BBB, com depoimentos exclusivos dos Brothers.(n)</desc>
    <date>2016</date>
    <category lang="en">Entretenimento</category>
    <category lang="en">Game show</category>
    <icon src="https://oisa.tmsimg.com/assets/p12470686_b_h10_ab.jpg" />
    <episode-num system="onscreen">S1 E14/20</episode-num>
    <rating>
      <value>12</value>
    </rating>
  </programme>
  <programme start="20210120210000 -0300" stop="20210120213000 -0300" channel="MULTISHOW">
    <title lang="en">Roteiro das Ondas - Indonésia</title>
    <sub-title lang="en">Nas Ondas de Nusa Lembongan - Bali</sub-title>
    <desc lang="en">A ilha de Nusa Lembongan fica bem perto de Bali, com fácil acesso e é o tipo de lugar que vai além do surfe: menos urbanizado, com belezas naturais exorbitantes, perfeito para relaxar. Conheça outros lugares e ondas aos arredores da ilha.(n)</desc>
    <date>2018</date>
    <category lang="en">Aventura</category>
    <category lang="en">Viagem</category>
    <icon src="https://oisa.tmsimg.com/assets/p15547073_e_h11_aa.jpg" />
    <episode-num system="onscreen">E8</episode-num>
    <rating>
      <value>L</value>
    </rating>
  </programme>
  <programme start="20210120213000 -0300" stop="20210120230000 -0300" channel="MULTISHOW">
    <title lang="en">TVZ</title>
    <desc lang="en">Os melhores clipes nacionais e internacionais das paradas musicais. Cada música apresenta letra e legenda.(n)</desc>
    <category lang="en">Música</category>
    <category lang="en">Variedades</category>
    <icon src="https://oisa.tmsimg.com/assets/p498480_b_h10_ab.jpg" />
    <rating>
      <value>12</value>
    </rating>
  </programme>
  <programme start="20210120230000 -0300" stop="20210120232800 -0300" channel="MULTISHOW">
    <title lang="en">Além da Ilha</title>
    <desc lang="en">Guta continua atrás de pistas para provar suas desconfianças contra Theodoro. Enquanto isso, os hóspedes vão fazer uma trilha e ouvem barulho de tiros.(n)</desc>
    <credits>
      <actor role="Beto">Paulo Gustavo</actor>
      <actor role="Guta">Katiuscia Canoro</actor>
      <actor role="Sheila">Monique Alfradique</actor>
      <actor role="Bia">Letícia Lima</actor>
      <actor role="Cardoso">Gabriel Godoy</actor>
      <actor role="Theodoro">André Mattos</actor>
      <actor role="Tobias">Guilherme Piva</actor>
      <actor role="Inácio">Paulo Roque</actor>
      <actor role="Kenji Midoriya">Anderson Lau</actor>
      <actor role="Atílio Bueno">Breno Guimarães</actor>
      <writer>Andrea Batitucci</writer>
      <writer>Rosana Hermann</writer>
    </credits>
    <date>2018</date>
    <category lang="en">Comédia Dramática</category>
    <icon src="https://oisa.tmsimg.com/assets/p17155132_e_h10_aa.jpg" />
    <episode-num system="onscreen">S1 E7/10</episode-num>
    <rating>
      <value>12</value>
    </rating>
  </programme>
  <programme start="20210120232800 -0300" stop="20210121003000 -0300" channel="MULTISHOW">
    <title lang="en">Multi Tom</title>
    <sub-title lang="en">Os Parças</sub-title>
    <desc lang="en">Ribamar entrevista Os Parças e a bagunça toma conta do palco. No "Tá Ok, Brasília!(n)</desc>
    <credits>
      <actor>Tom Cavalcante</actor>
    </credits>
    <date>2019</date>
    <category lang="en">Comédia</category>
    <category lang="en">Entretenimento</category>
    <icon src="https://oisa.tmsimg.com/assets/p16838456_e_h10_aa.jpg" />
    <episode-num system="onscreen">S4 E6/13</episode-num>
    <rating>
      <value>14</value>
    </rating>
  </programme>
</tv>